email_tools_quick/__init__.py
email_tools_quick/base.py
email_tools_quick/common.py
email_tools_quick/data.py
email_tools_quick/error.py
email_tools_quick/mail.py
email_tools_quick/mixin.py
email_tools_quick/ms.py
email_tools_quick/utf7.py
email_tools_quick/utils.py
email_tools_quick-1.0.1.dist-info/METADATA
email_tools_quick-1.0.1.dist-info/WHEEL
email_tools_quick-1.0.1.dist-info/RECORD
