Metadata-Version: 2.4
Name: email-tools-quick
Version: 1.0.1
Summary: A collection of tools for email processing
Author-email: “Ge” <cosplox@outlook.com>
Requires-Python: >=3.10
Requires-Dist: beautifulsoup4
Requires-Dist: curl-cffi
Requires-Dist: dnspython>=2.7.0
Requires-Dist: loguru
Requires-Dist: pysocks
Requires-Dist: python-dateutil
